LICENSE
sphinx_rtd_size/__init__.py
sphinx_rtd_size/_static/css/sphinx_rtd_size.css_t
sphinx_rtd_size/extension.py
sphinx_rtd_size-0.2.0.dist-info/LICENSE
sphinx_rtd_size-0.2.0.dist-info/WHEEL
sphinx_rtd_size-0.2.0.dist-info/METADATA
sphinx_rtd_size-0.2.0.dist-info/RECORD
